README.md
setup.py
linksgql/__init__.py
linksgql/client.py
linksgql/exceptions.py
linksgql.egg-info/PKG-INFO
linksgql.egg-info/SOURCES.txt
linksgql.egg-info/dependency_links.txt
linksgql.egg-info/requires.txt
linksgql.egg-info/top_level.txt