Metadata-Version: 2.1
Name: linksgql
Version: 0.1.0
Summary: Data.Doublets.Gql
Home-page: https://github.com/linksplatform/Data.Doublets.Gql
Author: Ethosa
Author-email: social.ethosa@gmail.com
License: LGPLv3
Project-URL: Github, https://github.com/linksplatform/Data.Doublets.Gql
Project-URL: Documentation, https://github.com/linksplatform/Data.Doublets.Gql
Keywords: Python Gql
Platform: UNKNOWN
Classifier: Development Status :: 4 - Beta
Classifier: Programming Language :: Python :: 3
Classifier: Programming Language :: Python :: 3.4
Classifier: Programming Language :: Python :: 3.5
Classifier: Programming Language :: Python :: 3.6
Classifier: Programming Language :: Python :: 3.7
Classifier: License :: OSI Approved :: GNU Affero General Public License v3
Classifier: Operating System :: OS Independent
Requires-Python: >=3
